screenpy_selenium/__init__.py
screenpy_selenium/__version__.py
screenpy_selenium/abilities/__init__.py
screenpy_selenium/abilities/browse_the_web.py
screenpy_selenium/actions/__init__.py
screenpy_selenium/actions/accept_alert.py
screenpy_selenium/actions/chain.py
screenpy_selenium/actions/clear.py
screenpy_selenium/actions/click.py
screenpy_selenium/actions/dismiss_alert.py
screenpy_selenium/actions/double_click.py
screenpy_selenium/actions/enter.py
screenpy_selenium/actions/enter_2fa_token.py
screenpy_selenium/actions/go_back.py
screenpy_selenium/actions/go_forward.py
screenpy_selenium/actions/hold_down.py
screenpy_selenium/actions/move_mouse.py
screenpy_selenium/actions/open.py
screenpy_selenium/actions/pause.py
screenpy_selenium/actions/refresh_page.py
screenpy_selenium/actions/release.py
screenpy_selenium/actions/respond_to_the_prompt.py
screenpy_selenium/actions/right_click.py
screenpy_selenium/actions/save_console_log.py
screenpy_selenium/actions/save_screenshot.py
screenpy_selenium/actions/select.py
screenpy_selenium/actions/switch_to.py
screenpy_selenium/actions/switch_to_tab.py
screenpy_selenium/actions/wait.py
screenpy_selenium/exceptions.py
screenpy_selenium/protocols.py
screenpy_selenium/py.typed
screenpy_selenium/questions/__init__.py
screenpy_selenium/questions/attribute.py
screenpy_selenium/questions/browser_title.py
screenpy_selenium/questions/browser_url.py
screenpy_selenium/questions/cookies.py
screenpy_selenium/questions/element.py
screenpy_selenium/questions/list.py
screenpy_selenium/questions/number.py
screenpy_selenium/questions/selected.py
screenpy_selenium/questions/text.py
screenpy_selenium/questions/text_of_the_alert.py
screenpy_selenium/resolutions/__init__.py
screenpy_selenium/resolutions/custom_matchers/__init__.py
screenpy_selenium/resolutions/custom_matchers/is_clickable_element.py
screenpy_selenium/resolutions/custom_matchers/is_invisible_element.py
screenpy_selenium/resolutions/custom_matchers/is_present_element.py
screenpy_selenium-4.0.4.dist-info/LICENSE
screenpy_selenium-4.0.4.dist-info/METADATA
screenpy_selenium-4.0.4.dist-info/WHEEL
screenpy_selenium-4.0.4.dist-info/RECORD
